catnado_docgen/__init__.py
catnado_docgen/__main__.py
catnado_docgen/build.py
catnado_docgen/crawler.py
catnado_docgen/filewriter.py
catnado_docgen-0.0.1.dev2.dist-info/METADATA
catnado_docgen-0.0.1.dev2.dist-info/RECORD
catnado_docgen-0.0.1.dev2.dist-info/WHEEL
catnado_docgen-0.0.1.dev2.dist-info/entry_points.txt
catnado_docgen-0.0.1.dev2.dist-info/top_level.txt
