Metadata-Version: 2.1
Name: catnado-docgen
Version: 0.0.1.dev2
Summary: A Python documentation utility.
Home-page: http://github.com/tylertrussell/catnado-docgen
Author: Tyler Trussell
Author-email: tigertrussell+pip@gmail.com
License: Apache 2.0
Keywords: python documentation generation mkdocs
Platform: UNKNOWN
